{
  "000": "No precipitation",
  "001": "1 mm",
  "002": "2 mm",
  "003": "3 mm",
  "004": "4 mm",
  "005": "5 mm",
  "006": "6 mm",
  "007": "7 mm",
  "008": "8 mm",
  "009": "9 mm",
  "010": "10 mm",
  "011": "11 mm",
  "012": "12 mm",
  "013": "13 mm",
  "014": "14 mm",
  "015": "15 mm",
  "016": "16 mm",
  "017": "17 mm",
  "018": "18 mm",
  "019": "19 mm",
  "020": "20 mm",
  "021": "21 mm",
  "022": "22 mm",
  "023": "23 mm",
  "024": "24 mm",
  "025": "25 mm",
  "026": "26 mm",
  "027": "27 mm",
  "028": "28 mm",
  "029": "29 mm",
  "030": "30 mm",
  "031": "31 mm",
  "032": "32 mm",
  "033": "33 mm",
  "034": "34 mm",
  "035": "35 mm",
  "036": "36 mm",
  "037": "37 mm",
  "038": "38 mm",
  "039": "39 mm",
  "040": "40 mm",
  "041": "41 mm",
  "042": "42 mm",
  "043": "43 mm",
  "044": "44 mm",
  "045": "45 mm",
  "046": "46 mm",
  "047": "47 mm",
  "048": "48 mm",
  "049": "49 mm",
  "050": "50 mm",
  "051": "51 mm",
  "052": "52 mm",
  "053": "53 mm",
  "054": "54 mm",
  "055": "55 mm",
  "056": "56 mm",
  "057": "57 mm",
  "058": "58 mm",
  "059": "59 mm",
  "060": "60 mm",
  "061": "61 mm",
  "062": "62 mm",
  "063": "63 mm",
  "064": "64 mm",
  "065": "65 mm",
  "066": "66 mm",
  "067": "67 mm",
  "068": "68 mm",
  "069": "69 mm",
  "070": "70 mm",
  "071": "71 mm",
  "072": "72 mm",
  "073": "73 mm",
  "074": "74 mm",
  "075": "75 mm",
  "076": "76 mm",
  "077": "77 mm",
  "078": "78 mm",
  "079": "79 mm",
  "080": "80 mm",
  "081": "81 mm",
  "082": "82 mm",
  "083": "83 mm",
  "084": "84 mm",
  "085": "85 mm",
  "086": "86 mm",
  "087": "87 mm",
  "088": "88 mm",
  "089": "89 mm",
  "090": "90 mm",
  "091": "91 mm",
  "092": "92 mm",
  "093": "93 mm",
  "094": "94 mm",
  "095": "95 mm",
  "096": "96 mm",
  "097": "97 mm",
  "098": "98 mm",
  "099": "99 mm",
  "100": "100 mm",
  "101": "101 mm",
  "102": "102 mm",
  "103": "103 mm",
  "104": "104 mm",
  "105": "105 mm",
  "106": "106 mm",
  "107": "107 mm",
  "108": "108 mm",
  "109": "109 mm",
  "110": "110 mm",
  "111": "111 mm",
  "112": "112 mm",
  "113": "113 mm",
  "114": "114 mm",
  "115": "115 mm",
  "116": "116 mm",
  "117": "117 mm",
  "118": "118 mm",
  "119": "119 mm",
  "120": "120 mm",
  "121": "121 mm",
  "122": "122 mm",
  "123": "123 mm",
  "124": "124 mm",
  "125": "125 mm",
  "126": "126 mm",
  "127": "127 mm",
  "128": "128 mm",
  "129": "129 mm",
  "130": "130 mm",
  "131": "131 mm",
  "132": "132 mm",
  "133": "133 mm",
  "134": "134 mm",
  "135": "135 mm",
  "136": "136 mm",
  "137": "137 mm",
  "138": "138 mm",
  "139": "139 mm",
  "140": "140 mm",
  "141": "141 mm",
  "142": "142 mm",
  "143": "143 mm",
  "144": "144 mm",
  "145": "145 mm",
  "146": "146 mm",
  "147": "147 mm",
  "148": "148 mm",
  "149": "149 mm",
  "150": "150 mm",
  "151": "151 mm",
  "152": "152 mm",
  "153": "153 mm",
  "154": "154 mm",
  "155": "155 mm",
  "156": "156 mm",
  "157": "157 mm",
  "158": "158 mm",
  "159": "159 mm",
  "160": "160 mm",
  "161": "161 mm",
  "162": "162 mm",
  "163": "163 mm",
  "164": "164 mm",
  "165": "165 mm",
  "166": "166 mm",
  "167": "167 mm",
  "168": "168 mm",
  "169": "169 mm",
  "170": "170 mm",
  "171": "171 mm",
  "172": "172 mm",
  "173": "173 mm",
  "174": "174 mm",
  "175": "175 mm",
  "176": "176 mm",
  "177": "177 mm",
  "178": "178 mm",
  "179": "179 mm",
  "180": "180 mm",
  "181": "181 mm",
  "182": "182 mm",
  "183": "183 mm",
  "184": "184 mm",
  "185": "185 mm",
  "186": "186 mm",
  "187": "187 mm",
  "188": "188 mm",
  "189": "189 mm",
  "190": "190 mm",
  "191": "191 mm",
  "192": "192 mm",
  "193": "193 mm",
  "194": "194 mm",
  "195": "195 mm",
  "196": "196 mm",
  "197": "197 mm",
  "198": "198 mm",
  "199": "199 mm",
  "200": "200 mm",
  "201": "201 mm",
  "202": "202 mm",
  "203": "203 mm",
  "204": "204 mm",
  "205": "205 mm",
  "206": "206 mm",
  "207": "207 mm",
  "208": "208 mm",
  "209": "209 mm",
  "210": "210 mm",
  "211": "211 mm",
  "212": "212 mm",
  "213": "213 mm",
  "214": "214 mm",
  "215": "215 mm",
  "216": "216 mm",
  "217": "217 mm",
  "218": "218 mm",
  "219": "219 mm",
  "220": "220 mm",
  "221": "221 mm",
  "222": "222 mm",
  "223": "223 mm",
  "224": "224 mm",
  "225": "225 mm",
  "226": "226 mm",
  "227": "227 mm",
  "228": "228 mm",
  "229": "229 mm",
  "230": "230 mm",
  "231": "231 mm",
  "232": "232 mm",
  "233": "233 mm",
  "234": "234 mm",
  "235": "235 mm",
  "236": "236 mm",
  "237": "237 mm",
  "238": "238 mm",
  "239": "239 mm",
  "240": "240 mm",
  "241": "241 mm",
  "242": "242 mm",
  "243": "243 mm",
  "244": "244 mm",
  "245": "245 mm",
  "246": "246 mm",
  "247": "247 mm",
  "248": "248 mm",
  "249": "249 mm",
  "250": "250 mm",
  "251": "251 mm",
  "252": "252 mm",
  "253": "253 mm",
  "254": "254 mm",
  "255": "255 mm",
  "256": "256 mm",
  "257": "257 mm",
  "258": "258 mm",
  "259": "259 mm",
  "260": "260 mm",
  "261": "261 mm",
  "262": "262 mm",
  "263": "263 mm",
  "264": "264 mm",
  "265": "265 mm",
  "266": "266 mm",
  "267": "267 mm",
  "268": "268 mm",
  "269": "269 mm",
  "270": "270 mm",
  "271": "271 mm",
  "272": "272 mm",
  "273": "273 mm",
  "274": "274 mm",
  "275": "275 mm",
  "276": "276 mm",
  "277": "277 mm",
  "278": "278 mm",
  "279": "279 mm",
  "280": "280 mm",
  "281": "281 mm",
  "282": "282 mm",
  "283": "283 mm",
  "284": "284 mm",
  "285": "285 mm",
  "286": "286 mm",
  "287": "287 mm",
  "288": "288 mm",
  "289": "289 mm",
  "290": "290 mm",
  "291": "291 mm",
  "292": "292 mm",
  "293": "293 mm",
  "294": "294 mm",
  "295": "295 mm",
  "296": "296 mm",
  "297": "297 mm",
  "298": "298 mm",
  "299": "299 mm",
  "300": "300 mm",
  "301": "301 mm",
  "302": "302 mm",
  "303": "303 mm",
  "304": "304 mm",
  "305": "305 mm",
  "306": "306 mm",
  "307": "307 mm",
  "308": "308 mm",
  "309": "309 mm",
  "310": "310 mm",
  "311": "311 mm",
  "312": "312 mm",
  "313": "313 mm",
  "314": "314 mm",
  "315": "315 mm",
  "316": "316 mm",
  "317": "317 mm",
  "318": "318 mm",
  "319": "319 mm",
  "320": "320 mm",
  "321": "321 mm",
  "322": "322 mm",
  "323": "323 mm",
  "324": "324 mm",
  "325": "325 mm",
  "326": "326 mm",
  "327": "327 mm",
  "328": "328 mm",
  "329": "329 mm",
  "330": "330 mm",
  "331": "331 mm",
  "332": "332 mm",
  "333": "333 mm",
  "334": "334 mm",
  "335": "335 mm",
  "336": "336 mm",
  "337": "337 mm",
  "338": "338 mm",
  "339": "339 mm",
  "340": "340 mm",
  "341": "341 mm",
  "342": "342 mm",
  "343": "343 mm",
  "344": "344 mm",
  "345": "345 mm",
  "346": "346 mm",
  "347": "347 mm",
  "348": "348 mm",
  "349": "349 mm",
  "350": "350 mm",
  "351": "351 mm",
  "352": "352 mm",
  "353": "353 mm",
  "354": "354 mm",
  "355": "355 mm",
  "356": "356 mm",
  "357": "357 mm",
  "358": "358 mm",
  "359": "359 mm",
  "360": "360 mm",
  "361": "361 mm",
  "362": "362 mm",
  "363": "363 mm",
  "364": "364 mm",
  "365": "365 mm",
  "366": "366 mm",
  "367": "367 mm",
  "368": "368 mm",
  "369": "369 mm",
  "370": "370 mm",
  "371": "371 mm",
  "372": "372 mm",
  "373": "373 mm",
  "374": "374 mm",
  "375": "375 mm",
  "376": "376 mm",
  "377": "377 mm",
  "378": "378 mm",
  "379": "379 mm",
  "380": "380 mm",
  "381": "381 mm",
  "382": "382 mm",
  "383": "383 mm",
  "384": "384 mm",
  "385": "385 mm",
  "386": "386 mm",
  "387": "387 mm",
  "388": "388 mm",
  "389": "389 mm",
  "390": "390 mm",
  "391": "391 mm",
  "392": "392 mm",
  "393": "393 mm",
  "394": "394 mm",
  "395": "395 mm",
  "396": "396 mm",
  "397": "397 mm",
  "398": "398 mm",
  "399": "399 mm",
  "400": "400 mm",
  "401": "401 mm",
  "402": "402 mm",
  "403": "403 mm",
  "404": "404 mm",
  "405": "405 mm",
  "406": "406 mm",
  "407": "407 mm",
  "408": "408 mm",
  "409": "409 mm",
  "410": "410 mm",
  "411": "411 mm",
  "412": "412 mm",
  "413": "413 mm",
  "414": "414 mm",
  "415": "415 mm",
  "416": "416 mm",
  "417": "417 mm",
  "418": "418 mm",
  "419": "419 mm",
  "420": "420 mm",
  "421": "421 mm",
  "422": "422 mm",
  "423": "423 mm",
  "424": "424 mm",
  "425": "425 mm",
  "426": "426 mm",
  "427": "427 mm",
  "428": "428 mm",
  "429": "429 mm",
  "430": "430 mm",
  "431": "431 mm",
  "432": "432 mm",
  "433": "433 mm",
  "434": "434 mm",
  "435": "435 mm",
  "436": "436 mm",
  "437": "437 mm",
  "438": "438 mm",
  "439": "439 mm",
  "440": "440 mm",
  "441": "441 mm",
  "442": "442 mm",
  "443": "443 mm",
  "444": "444 mm",
  "445": "445 mm",
  "446": "446 mm",
  "447": "447 mm",
  "448": "448 mm",
  "449": "449 mm",
  "450": "450 mm",
  "451": "451 mm",
  "452": "452 mm",
  "453": "453 mm",
  "454": "454 mm",
  "455": "455 mm",
  "456": "456 mm",
  "457": "457 mm",
  "458": "458 mm",
  "459": "459 mm",
  "460": "460 mm",
  "461": "461 mm",
  "462": "462 mm",
  "463": "463 mm",
  "464": "464 mm",
  "465": "465 mm",
  "466": "466 mm",
  "467": "467 mm",
  "468": "468 mm",
  "469": "469 mm",
  "470": "470 mm",
  "471": "471 mm",
  "472": "472 mm",
  "473": "473 mm",
  "474": "474 mm",
  "475": "475 mm",
  "476": "476 mm",
  "477": "477 mm",
  "478": "478 mm",
  "479": "479 mm",
  "480": "480 mm",
  "481": "481 mm",
  "482": "482 mm",
  "483": "483 mm",
  "484": "484 mm",
  "485": "485 mm",
  "486": "486 mm",
  "487": "487 mm",
  "488": "488 mm",
  "489": "489 mm",
  "490": "490 mm",
  "491": "491 mm",
  "492": "492 mm",
  "493": "493 mm",
  "494": "494 mm",
  "495": "495 mm",
  "496": "496 mm",
  "497": "497 mm",
  "498": "498 mm",
  "499": "499 mm",
  "500": "500 mm",
  "501": "501 mm",
  "502": "502 mm",
  "503": "503 mm",
  "504": "504 mm",
  "505": "505 mm",
  "506": "506 mm",
  "507": "507 mm",
  "508": "508 mm",
  "509": "509 mm",
  "510": "510 mm",
  "511": "511 mm",
  "512": "512 mm",
  "513": "513 mm",
  "514": "514 mm",
  "515": "515 mm",
  "516": "516 mm",
  "517": "517 mm",
  "518": "518 mm",
  "519": "519 mm",
  "520": "520 mm",
  "521": "521 mm",
  "522": "522 mm",
  "523": "523 mm",
  "524": "524 mm",
  "525": "525 mm",
  "526": "526 mm",
  "527": "527 mm",
  "528": "528 mm",
  "529": "529 mm",
  "530": "530 mm",
  "531": "531 mm",
  "532": "532 mm",
  "533": "533 mm",
  "534": "534 mm",
  "535": "535 mm",
  "536": "536 mm",
  "537": "537 mm",
  "538": "538 mm",
  "539": "539 mm",
  "540": "540 mm",
  "541": "541 mm",
  "542": "542 mm",
  "543": "543 mm",
  "544": "544 mm",
  "545": "545 mm",
  "546": "546 mm",
  "547": "547 mm",
  "548": "548 mm",
  "549": "549 mm",
  "550": "550 mm",
  "551": "551 mm",
  "552": "552 mm",
  "553": "553 mm",
  "554": "554 mm",
  "555": "555 mm",
  "556": "556 mm",
  "557": "557 mm",
  "558": "558 mm",
  "559": "559 mm",
  "560": "560 mm",
  "561": "561 mm",
  "562": "562 mm",
  "563": "563 mm",
  "564": "564 mm",
  "565": "565 mm",
  "566": "566 mm",
  "567": "567 mm",
  "568": "568 mm",
  "569": "569 mm",
  "570": "570 mm",
  "571": "571 mm",
  "572": "572 mm",
  "573": "573 mm",
  "574": "574 mm",
  "575": "575 mm",
  "576": "576 mm",
  "577": "577 mm",
  "578": "578 mm",
  "579": "579 mm",
  "580": "580 mm",
  "581": "581 mm",
  "582": "582 mm",
  "583": "583 mm",
  "584": "584 mm",
  "585": "585 mm",
  "586": "586 mm",
  "587": "587 mm",
  "588": "588 mm",
  "589": "589 mm",
  "590": "590 mm",
  "591": "591 mm",
  "592": "592 mm",
  "593": "593 mm",
  "594": "594 mm",
  "595": "595 mm",
  "596": "596 mm",
  "597": "597 mm",
  "598": "598 mm",
  "599": "599 mm",
  "600": "600 mm",
  "601": "601 mm",
  "602": "602 mm",
  "603": "603 mm",
  "604": "604 mm",
  "605": "605 mm",
  "606": "606 mm",
  "607": "607 mm",
  "608": "608 mm",
  "609": "609 mm",
  "610": "610 mm",
  "611": "611 mm",
  "612": "612 mm",
  "613": "613 mm",
  "614": "614 mm",
  "615": "615 mm",
  "616": "616 mm",
  "617": "617 mm",
  "618": "618 mm",
  "619": "619 mm",
  "620": "620 mm",
  "621": "621 mm",
  "622": "622 mm",
  "623": "623 mm",
  "624": "624 mm",
  "625": "625 mm",
  "626": "626 mm",
  "627": "627 mm",
  "628": "628 mm",
  "629": "629 mm",
  "630": "630 mm",
  "631": "631 mm",
  "632": "632 mm",
  "633": "633 mm",
  "634": "634 mm",
  "635": "635 mm",
  "636": "636 mm",
  "637": "637 mm",
  "638": "638 mm",
  "639": "639 mm",
  "640": "640 mm",
  "641": "641 mm",
  "642": "642 mm",
  "643": "643 mm",
  "644": "644 mm",
  "645": "645 mm",
  "646": "646 mm",
  "647": "647 mm",
  "648": "648 mm",
  "649": "649 mm",
  "650": "650 mm",
  "651": "651 mm",
  "652": "652 mm",
  "653": "653 mm",
  "654": "654 mm",
  "655": "655 mm",
  "656": "656 mm",
  "657": "657 mm",
  "658": "658 mm",
  "659": "659 mm",
  "660": "660 mm",
  "661": "661 mm",
  "662": "662 mm",
  "663": "663 mm",
  "664": "664 mm",
  "665": "665 mm",
  "666": "666 mm",
  "667": "667 mm",
  "668": "668 mm",
  "669": "669 mm",
  "670": "670 mm",
  "671": "671 mm",
  "672": "672 mm",
  "673": "673 mm",
  "674": "674 mm",
  "675": "675 mm",
  "676": "676 mm",
  "677": "677 mm",
  "678": "678 mm",
  "679": "679 mm",
  "680": "680 mm",
  "681": "681 mm",
  "682": "682 mm",
  "683": "683 mm",
  "684": "684 mm",
  "685": "685 mm",
  "686": "686 mm",
  "687": "687 mm",
  "688": "688 mm",
  "689": "689 mm",
  "690": "690 mm",
  "691": "691 mm",
  "692": "692 mm",
  "693": "693 mm",
  "694": "694 mm",
  "695": "695 mm",
  "696": "696 mm",
  "697": "697 mm",
  "698": "698 mm",
  "699": "699 mm",
  "700": "700 mm",
  "701": "701 mm",
  "702": "702 mm",
  "703": "703 mm",
  "704": "704 mm",
  "705": "705 mm",
  "706": "706 mm",
  "707": "707 mm",
  "708": "708 mm",
  "709": "709 mm",
  "710": "710 mm",
  "711": "711 mm",
  "712": "712 mm",
  "713": "713 mm",
  "714": "714 mm",
  "715": "715 mm",
  "716": "716 mm",
  "717": "717 mm",
  "718": "718 mm",
  "719": "719 mm",
  "720": "720 mm",
  "721": "721 mm",
  "722": "722 mm",
  "723": "723 mm",
  "724": "724 mm",
  "725": "725 mm",
  "726": "726 mm",
  "727": "727 mm",
  "728": "728 mm",
  "729": "729 mm",
  "730": "730 mm",
  "731": "731 mm",
  "732": "732 mm",
  "733": "733 mm",
  "734": "734 mm",
  "735": "735 mm",
  "736": "736 mm",
  "737": "737 mm",
  "738": "738 mm",
  "739": "739 mm",
  "740": "740 mm",
  "741": "741 mm",
  "742": "742 mm",
  "743": "743 mm",
  "744": "744 mm",
  "745": "745 mm",
  "746": "746 mm",
  "747": "747 mm",
  "748": "748 mm",
  "749": "749 mm",
  "750": "750 mm",
  "751": "751 mm",
  "752": "752 mm",
  "753": "753 mm",
  "754": "754 mm",
  "755": "755 mm",
  "756": "756 mm",
  "757": "757 mm",
  "758": "758 mm",
  "759": "759 mm",
  "760": "760 mm",
  "761": "761 mm",
  "762": "762 mm",
  "763": "763 mm",
  "764": "764 mm",
  "765": "765 mm",
  "766": "766 mm",
  "767": "767 mm",
  "768": "768 mm",
  "769": "769 mm",
  "770": "770 mm",
  "771": "771 mm",
  "772": "772 mm",
  "773": "773 mm",
  "774": "774 mm",
  "775": "775 mm",
  "776": "776 mm",
  "777": "777 mm",
  "778": "778 mm",
  "779": "779 mm",
  "780": "780 mm",
  "781": "781 mm",
  "782": "782 mm",
  "783": "783 mm",
  "784": "784 mm",
  "785": "785 mm",
  "786": "786 mm",
  "787": "787 mm",
  "788": "788 mm",
  "789": "789 mm",
  "790": "790 mm",
  "791": "791 mm",
  "792": "792 mm",
  "793": "793 mm",
  "794": "794 mm",
  "795": "795 mm",
  "796": "796 mm",
  "797": "797 mm",
  "798": "798 mm",
  "799": "799 mm",
  "800": "800 mm",
  "801": "801 mm",
  "802": "802 mm",
  "803": "803 mm",
  "804": "804 mm",
  "805": "805 mm",
  "806": "806 mm",
  "807": "807 mm",
  "808": "808 mm",
  "809": "809 mm",
  "810": "810 mm",
  "811": "811 mm",
  "812": "812 mm",
  "813": "813 mm",
  "814": "814 mm",
  "815": "815 mm",
  "816": "816 mm",
  "817": "817 mm",
  "818": "818 mm",
  "819": "819 mm",
  "820": "820 mm",
  "821": "821 mm",
  "822": "822 mm",
  "823": "823 mm",
  "824": "824 mm",
  "825": "825 mm",
  "826": "826 mm",
  "827": "827 mm",
  "828": "828 mm",
  "829": "829 mm",
  "830": "830 mm",
  "831": "831 mm",
  "832": "832 mm",
  "833": "833 mm",
  "834": "834 mm",
  "835": "835 mm",
  "836": "836 mm",
  "837": "837 mm",
  "838": "838 mm",
  "839": "839 mm",
  "840": "840 mm",
  "841": "841 mm",
  "842": "842 mm",
  "843": "843 mm",
  "844": "844 mm",
  "845": "845 mm",
  "846": "846 mm",
  "847": "847 mm",
  "848": "848 mm",
  "849": "849 mm",
  "850": "850 mm",
  "851": "851 mm",
  "852": "852 mm",
  "853": "853 mm",
  "854": "854 mm",
  "855": "855 mm",
  "856": "856 mm",
  "857": "857 mm",
  "858": "858 mm",
  "859": "859 mm",
  "860": "860 mm",
  "861": "861 mm",
  "862": "862 mm",
  "863": "863 mm",
  "864": "864 mm",
  "865": "865 mm",
  "866": "866 mm",
  "867": "867 mm",
  "868": "868 mm",
  "869": "869 mm",
  "870": "870 mm",
  "871": "871 mm",
  "872": "872 mm",
  "873": "873 mm",
  "874": "874 mm",
  "875": "875 mm",
  "876": "876 mm",
  "877": "877 mm",
  "878": "878 mm",
  "879": "879 mm",
  "880": "880 mm",
  "881": "881 mm",
  "882": "882 mm",
  "883": "883 mm",
  "884": "884 mm",
  "885": "885 mm",
  "886": "886 mm",
  "887": "887 mm",
  "888": "888 mm",
  "889": "889 mm",
  "890": "890 mm",
  "891": "891 mm",
  "892": "892 mm",
  "893": "893 mm",
  "894": "894 mm",
  "895": "895 mm",
  "896": "896 mm",
  "897": "897 mm",
  "898": "898 mm",
  "899": "899 mm",
  "900": "900 mm",
  "901": "901 mm",
  "902": "902 mm",
  "903": "903 mm",
  "904": "904 mm",
  "905": "905 mm",
  "906": "906 mm",
  "907": "907 mm",
  "908": "908 mm",
  "909": "909 mm",
  "910": "910 mm",
  "911": "911 mm",
  "912": "912 mm",
  "913": "913 mm",
  "914": "914 mm",
  "915": "915 mm",
  "916": "916 mm",
  "917": "917 mm",
  "918": "918 mm",
  "919": "919 mm",
  "920": "920 mm",
  "921": "921 mm",
  "922": "922 mm",
  "923": "923 mm",
  "924": "924 mm",
  "925": "925 mm",
  "926": "926 mm",
  "927": "927 mm",
  "928": "928 mm",
  "929": "929 mm",
  "930": "930 mm",
  "931": "931 mm",
  "932": "932 mm",
  "933": "933 mm",
  "934": "934 mm",
  "935": "935 mm",
  "936": "936 mm",
  "937": "937 mm",
  "938": "938 mm",
  "939": "939 mm",
  "940": "940 mm",
  "941": "941 mm",
  "942": "942 mm",
  "943": "943 mm",
  "944": "944 mm",
  "945": "945 mm",
  "946": "946 mm",
  "947": "947 mm",
  "948": "948 mm",
  "949": "949 mm",
  "950": "950 mm",
  "951": "951 mm",
  "952": "952 mm",
  "953": "953 mm",
  "954": "954 mm",
  "955": "955 mm",
  "956": "956 mm",
  "957": "957 mm",
  "958": "958 mm",
  "959": "959 mm",
  "960": "960 mm",
  "961": "961 mm",
  "962": "962 mm",
  "963": "963 mm",
  "964": "964 mm",
  "965": "965 mm",
  "966": "966 mm",
  "967": "967 mm",
  "968": "968 mm",
  "969": "969 mm",
  "970": "970 mm",
  "971": "971 mm",
  "972": "972 mm",
  "973": "973 mm",
  "974": "974 mm",
  "975": "975 mm",
  "976": "976 mm",
  "977": "977 mm",
  "978": "978 mm",
  "979": "979 mm",
  "980": "980 mm",
  "981": "981 mm",
  "982": "982 mm",
  "983": "983 mm",
  "984": "984 mm",
  "985": "985 mm",
  "986": "986 mm",
  "987": "987 mm",
  "988": "988 mm",
  "989": "989 mm or more",
  "990": "Trace",
  "991": "0.1 mm",
  "992": "0.2 mm",
  "993": "0.3 mm",
  "994": "0.4 mm",
  "995": "0.5 mm",
  "996": "0.6 mm",
  "997": "0.7 mm",
  "998": "0.8 mm",
  "999": "0.9 mm"
}
